LICENSE
MANIFEST.in
readme.md
requirements.txt
setup.py
docs/blank.txt
web3_authentication_django.egg-info/PKG-INFO
web3_authentication_django.egg-info/SOURCES.txt
web3_authentication_django.egg-info/dependency_links.txt
web3_authentication_django.egg-info/requires.txt
web3_authentication_django.egg-info/top_level.txt
web3auth/__init__.py
web3auth/apps.py
web3auth/backend.py
web3auth/forms.py
web3auth/readme.md
web3auth/settings.py
web3auth/urls.py
web3auth/utils.py
web3auth/views.py
web3auth/static/web3auth/css/web3auth.css
web3auth/static/web3auth/js/web3auth.js
web3auth/templates/web3auth/base.html
web3auth/templates/web3auth/signup.html