Metadata-Version: 2.1
Name: web3-authentication-django
Version: 0.3
Summary: A Django app to easily connect web3 authentication to your existing Django projects.
Home-page: https://github.com/ahn1305/web3-django-authentication
Author: Ashwin B
Author-email: ahnashwin1305@gmail.com
License: MIT
Classifier: Environment :: Web Environment
Classifier: Framework :: Django
Classifier: Framework :: Django :: 3
Classifier: Intended Audience :: Developers
Classifier: License :: OSI Approved :: MIT License
Classifier: Operating System :: OS Independent
Classifier: Programming Language :: Python
Classifier: Programming Language :: Python :: 3
Classifier: Topic :: Internet :: WWW/HTTP
Classifier: Topic :: Internet :: WWW/HTTP :: Dynamic Content
License-File: LICENSE
